pyplating/__init__.py
pyplating-0.1.dist-info/LICENSE
pyplating-0.1.dist-info/METADATA
pyplating-0.1.dist-info/WHEEL
pyplating-0.1.dist-info/top_level.txt
pyplating-0.1.dist-info/RECORD
