Metadata-Version: 2.1
Name: pyplating
Version: 0.1
Summary: Python templating library with support for nesting
Home-page: https://github.com/WiredSound/pyplating
Author: Max Black
Author-email: maxoblack@yahoo.com
License: UNKNOWN
Platform: UNKNOWN
Classifier: Programming Language :: Python :: 3
Classifier: Operating System :: OS Independent
Requires-Python: >=3.6
